setprint/SetPrint.py
setprint/__init__.py
setprint-0.1.11.dist-info/METADATA
setprint-0.1.11.dist-info/WHEEL
setprint-0.1.11.dist-info/top_level.txt
setprint-0.1.11.dist-info/RECORD
