Metadata-Version: 2.1
Name: setprint
Version: 0.1.11
Summary: A module that organizes the contents of a list and visualizes its hierarchical structure.  
Home-page: https://github.com/mtur2007/SetPrint
Author: mtur
Author-email: 2007helloworld@gmail.com
Project-URL: Bug Reports, https://github.com/mtur2007/SetPrint/issues
Project-URL: Source, https://github.com/mtur2007/SetPrint
Keywords: list,formatting,printing,set
Classifier: Development Status :: 3 - Alpha
Classifier: Intended Audience :: Developers
Classifier: License :: OSI Approved :: MIT License
Classifier: Programming Language :: Python :: 3
Classifier: Programming Language :: Python :: 3.6
Classifier: Programming Language :: Python :: 3.7
Classifier: Programming Language :: Python :: 3.8
Classifier: Programming Language :: Python :: 3.9
Classifier: Programming Language :: Python :: 3.10
Classifier: Operating System :: OS Independent
Requires-Python: >=3.6
Requires-Dist: numpy
Requires-Dist: pynput
